{"exit_score": 15.2, "btc_d": 56.7, "t3": 0.82, "portfolio": 11958.0, "multiplier": 0.1, "exit_apr": 542137.78, "exit_mai": 823117.11, "coins": [{"symbol": "OP", "price": 0.19391, "value": 1241.0, "apr": 4.8, "mai": 5.7, "pot": 29.4}, {"symbol": "NOT", "price": 0.00041114, "value": 533.0, "apr": 0.028, "mai": 0.03, "pot": 73.0}, {"symbol": "ARB", "price": 0.118755, "value": 1701.0, "apr": 3.0, "mai": 3.6, "pot": 30.3}, {"symbol": "TIA", "price": 0.345296, "value": 1555.0, "apr": 12.0, "mai": 16.0, "pot": 46.3}, {"symbol": "JTO", "price": 0.273941, "value": 2018.0, "apr": 8.0, "mai": 8.0, "pot": 29.2}, {"symbol": "LDO", "price": 0.355346, "value": 3304.0, "apr": 5.6, "mai": 6.8, "pot": 19.1}, {"symbol": "CTSI", "price": 0.0273229, "value": 1341.0, "apr": 0.2, "mai": 0.2, "pot": 7.3}, {"symbol": "IMX", "price": 0.17021, "value": 264.0, "apr": 3.5, "mai": 4.5, "pot": 26.4}]}